relm/__init__.py
relm/banner.py
relm/changelog.py
relm/clean.py
relm/config.py
relm/core.py
relm/gc.py
relm/git_ops.py
relm/install.py
relm/main.py
relm/release.py
relm/runner.py
relm/verify.py
relm/versioning.py
relm/commands/__init__.py
relm/commands/base.py
relm/commands/clean_command.py
relm/commands/create_command.py
relm/commands/gc_command.py
relm/commands/install_command.py
relm/commands/list_command.py
relm/commands/pytest_command.py
relm/commands/release_command.py
relm/commands/run_command.py
relm/commands/status_command.py
relm/commands/verify_command.py
relm-7.1.0.dist-info/METADATA
relm-7.1.0.dist-info/WHEEL
relm-7.1.0.dist-info/entry_points.txt
relm-7.1.0.dist-info/top_level.txt
relm-7.1.0.dist-info/RECORD
