Metadata-Version: 2.4
Name: relm
Version: 7.1.0
Summary: The Monorepo Manager for Python. A unified CLI for managing, testing, and releasing multi-project workspaces.
Author-email: dhruv13x <dhruv13x@gmail.com>
License: MIT © dhruv13x
Project-URL: Homepage, https://github.com/dhruv13x/relm
Project-URL: Source, https://github.com/dhruv13x/relm
Project-URL: Issues, https://github.com/dhruv13x/relm/issues
Keywords: cli,release,versioning,automation,pypi,git
Classifier: License :: OSI Approved :: MIT License
Classifier: Programming Language :: Python :: 3
Classifier: Programming Language :: Python :: 3 :: Only
Classifier: Environment :: Console
Classifier: Topic :: Software Development :: Build Tools
Requires-Python: >=3.8
Requires-Dist: tomli; python_version < "3.11"
Requires-Dist: rich>=13.0.0
Requires-Dist: rich-argparse>=1.0.0
Requires-Dist: build>=1.0.0
Requires-Dist: twine>=4.0.0
Requires-Dist: pyfakefs>=5.10.2
Provides-Extra: dev
Requires-Dist: pytest>=8.0.0; extra == "dev"
Requires-Dist: pytest-cov>=5.0.0; extra == "dev"
Requires-Dist: pytest-timeout>=2.2.0; extra == "dev"
Requires-Dist: pytest-json-report>=1.5.0; extra == "dev"
Requires-Dist: pytest-asyncio>=0.23.0; extra == "dev"
Requires-Dist: pytest-mock>=3.10.0; extra == "dev"
Requires-Dist: pyfakefs>=5.0.0; extra == "dev"
Requires-Dist: ruff>=0.6.0; extra == "dev"
Requires-Dist: black>=24.3.0; extra == "dev"
Requires-Dist: mypy>=1.11.0; extra == "dev"
Requires-Dist: PyYAML>=6.0; extra == "dev"
Requires-Dist: types-PyYAML>=6.0; extra == "dev"
